Metadata-Version: 2.1
Name: sample-metadata
Version: 5.7.2
Summary: Python API for interacting with the Sample API system
Home-page: https://github.com/populationgenomics/sample-metadata
License: MIT
Keywords: bioinformatics
Classifier: Environment :: Console
Classifier: Intended Audience :: Science/Research
Classifier: License :: OSI Approved :: MIT License
Classifier: Natural Language :: English
Classifier: Operating System :: MacOS :: MacOS X
Classifier: Operating System :: POSIX
Classifier: Operating System :: Unix
Classifier: Programming Language :: Python
Classifier: Topic :: Scientific/Engineering
Classifier: Topic :: Scientific/Engineering :: Bio-Informatics
License-File: LICENSE
